{
  "version": "1.0",
  "created_at": 1777042881.177321,
  "stage": "TRIGGER_ROUTER_EVALUATION",
  "request": "research current best practices, audit /mnt/data, understand the root cause, patch code, update registry, and export zip",
  "matched_routes": [
    "research_required",
    "sandbox_tool_required",
    "ce_required",
    "code_patch_required",
    "registry_mutation_required",
    "export_required"
  ],
  "required_stages": [
    "BOOT",
    "RESEARCH_TRIGGER_CHECK",
    "SEE_PASS",
    "TOOL_GOVERNANCE_CHECK",
    "CE_COMPREHENSION_PASS",
    "PLAN",
    "EXECUTE_ONE_STAGE",
    "VERIFY",
    "RECEIPT",
    "GIT_COMMIT"
  ],
  "required_modules": [
    "research_trigger",
    "sandbox_tool_governance",
    "CE_stage_cartridge",
    "script_quality_gate",
    "registry_mutation_engine",
    "export_guard"
  ],
  "pipeline_stage_validation": {
    "missing": []
  },
  "verdict": "PASS",
  "issues": [],
  "receipt_path": "/mnt/data/_boot_recovery_staging_SEE_D4_RERUN/Metablooms_OS_refined/0_kernel/registry/router_receipts/see_d4_recovery_rerun/ROUTER_RECEIPT_1777042881177.json"
}